pytest_xml/__init__.py
pytest_xml/hooks.py
pytest_xml/plugin.py
pytest_xml/py.typed
pytest_xml/report_data.py
pytest_xml/util.py
pytest_xml/version.py
pytest_xml/xml_report.py
pytest_xml/xml_template.xml.jinja
pytest_xml-0.1.1.dist-info/LICENSE
pytest_xml-0.1.1.dist-info/METADATA
pytest_xml-0.1.1.dist-info/WHEEL
pytest_xml-0.1.1.dist-info/entry_points.txt
pytest_xml-0.1.1.dist-info/top_level.txt
pytest_xml-0.1.1.dist-info/RECORD
