Metadata-Version: 2.1
Name: pytest-xml
Version: 0.1.1
Summary: Create simple XML results for parsing
Author-email: Adam Nogowski <anogowski@live.com>
Maintainer-email: Adam Nogowski <anogowski@live.com>
License: Dual License: All software and documentation is distributed under "BSD 3-Clause License" AND "Mozilla Public License Version 2.0"
Project-URL: Repository, https://github.com/anogowski/pytest-xml
Classifier: Framework :: Pytest
Classifier: Development Status :: 4 - Beta
Classifier: Intended Audience :: Developers
Classifier: Operating System :: OS Independent
Classifier: Programming Language :: Python
Classifier: Programming Language :: Python :: 3.11
Classifier: Programming Language :: Python :: 3.12
Classifier: Programming Language :: Python :: 3.13
Classifier: Programming Language :: Python :: 3 :: Only
Classifier: Programming Language :: Python :: Implementation :: CPython
Classifier: Programming Language :: Python :: Implementation :: PyPy
Classifier: License :: OSI Approved :: BSD License
Classifier: License :: OSI Approved :: Mozilla Public License 2.0 (MPL 2.0)
Classifier: Topic :: Software Development :: Quality Assurance
Classifier: Topic :: Software Development :: Testing
Classifier: Topic :: Utilities
Requires-Python: >=3.11
License-File: LICENSE
Requires-Dist: pytest>=8.0.0
Requires-Dist: pytest-metadata>=2.0.0
Requires-Dist: dict2xml>=1.7.6
Requires-Dist: jinja2>=3.0.0
